pywin_contextmenu.py
pywin_contextmenu-2021.1.7.dist-info/LICENSE
pywin_contextmenu-2021.1.7.dist-info/METADATA
pywin_contextmenu-2021.1.7.dist-info/WHEEL
pywin_contextmenu-2021.1.7.dist-info/top_level.txt
pywin_contextmenu-2021.1.7.dist-info/RECORD
