Metadata-Version: 2.1
Name: pywin-contextmenu
Version: 2021.1.7
Summary: A simple and intuitive way to add your custom scripts to the windows right click contextmenu.
Home-page: https://github.com/naveennamani/pywin_contextmenu
Author: Naveen Namani
Author-email: naveennamani877@gmail.com
License: UNKNOWN
Project-URL: Bug Reports, https://github.com/naveennamani/pywin_contextmenu/issues
Project-URL: Source, https://github.com/naveennamani/pywin_contextmenu/
Keywords: windows contextmenu customscripts contextmenu-organization windows-contextmenu-organization productivity-tools utility-tools
Platform: UNKNOWN
Classifier: Development Status :: 4 - Beta
Classifier: Intended Audience :: Developers
Classifier: License :: OSI Approved :: MIT License
Classifier: Programming Language :: Python :: 3
Classifier: Programming Language :: Python :: 3.5
Classifier: Programming Language :: Python :: 3.6
Classifier: Programming Language :: Python :: 3.7
Classifier: Programming Language :: Python :: 3.8
Classifier: Programming Language :: Python :: 3 :: Only
Requires-Python: >=3.5, <4
